autometrics_nonrel/__init__.py
autometrics_nonrel/functions.py
autometrics_nonrel/middleware.py
autometrics_nonrel/mixins.py
autometrics_nonrel/models.py
autometrics_nonrel/serializers.py
autometrics_nonrel/urls.py
autometrics_nonrel/tests/__init__.py
autometrics_nonrel/tests/functions.py
autometrics_nonrel/tests/middleware.py
autometrics_nonrel/tests/mixins.py
autometrics_nonrel/tests/models.py
autometrics_nonrel/tests/signals.py
autometrics_nonrel/tests/test.py
django_autometrics_nonrel-0.9.2b1.dist-info/DESCRIPTION.rst
django_autometrics_nonrel-0.9.2b1.dist-info/METADATA
django_autometrics_nonrel-0.9.2b1.dist-info/RECORD
django_autometrics_nonrel-0.9.2b1.dist-info/WHEEL
django_autometrics_nonrel-0.9.2b1.dist-info/metadata.json
django_autometrics_nonrel-0.9.2b1.dist-info/top_level.txt
