Metadata-Version: 2.0
Name: django-autometrics-nonrel
Version: 0.9.2b1
Summary: A Django+Djangae app to collect session and access metrics.
Home-page: https://github.com/seawolf42/django-autometrics
Author: jeffrey k eliasen
Author-email: jeff+django-autometrics@jke.net
License: MIT License
Keywords: django analytics
Platform: UNKNOWN
Classifier: Environment :: Web Environment
Classifier: Framework :: Django
Classifier: Framework :: Django :: 1.8
Classifier: Intended Audience :: Developers
Classifier: License :: OSI Approved :: MIT License
Classifier: Operating System :: OS Independent
Classifier: Programming Language :: Python
Classifier: Programming Language :: Python :: 2.7
Classifier: Topic :: System :: Logging
Requires-Dist: Django (>=1.8,<1.9)
Requires-Dist: djangae (==0.9.8)
